MANIFEST.in
README.rst
setup.py
src/lxsentencesplitter/__init__.py
src/lxsentencesplitter/__main__.py
src/lxsentencesplitter/lxsentencesplitter.py
src/lxsentencesplitter.egg-info/PKG-INFO
src/lxsentencesplitter.egg-info/SOURCES.txt
src/lxsentencesplitter.egg-info/dependency_links.txt
src/lxsentencesplitter.egg-info/entry_points.txt
src/lxsentencesplitter.egg-info/requires.txt
src/lxsentencesplitter.egg-info/top_level.txt
src/lxsentencesplitter/chunker/Makefile
src/lxsentencesplitter/chunker/README
src/lxsentencesplitter/chunker/chunker-one
src/lxsentencesplitter/chunker/chunker-two
src/lxsentencesplitter/chunker/chunker_one-nl.lex
src/lxsentencesplitter/chunker/chunker_two-nl.lex